bricks_helper/__init__.py
bricks_helper/bricks_helper.py
bricks_helper-1.2.5.dist-info/LICENSE.txt
bricks_helper-1.2.5.dist-info/METADATA
bricks_helper-1.2.5.dist-info/WHEEL
bricks_helper-1.2.5.dist-info/top_level.txt
bricks_helper-1.2.5.dist-info/RECORD
